py_rate_limiter_sean_ippolito/__init__.py
py_rate_limiter_sean_ippolito/db.py
py_rate_limiter_sean_ippolito/routes.py
py_rate_limiter_sean_ippolito-0.0.1.dist-info/LICENSE
py_rate_limiter_sean_ippolito-0.0.1.dist-info/METADATA
py_rate_limiter_sean_ippolito-0.0.1.dist-info/WHEEL
py_rate_limiter_sean_ippolito-0.0.1.dist-info/top_level.txt
py_rate_limiter_sean_ippolito-0.0.1.dist-info/RECORD
